ncmdump/__init__.py
ncmdump/__main__.py
ncmdump/core.py
ncmdump/crypto.py
ncmdump/logger.py
ncmdump_py-1.1.6.dist-info/licenses/LICENSE
ncmdump_py-1.1.6.dist-info/METADATA
ncmdump_py-1.1.6.dist-info/WHEEL
ncmdump_py-1.1.6.dist-info/top_level.txt
ncmdump_py-1.1.6.dist-info/RECORD
