Metadata-Version: 2.4
Name: ncmdump-py
Version: 1.1.6
Summary: Dump ncm files to mp3 or flac files.
Author-email: ww-rm <ww-rm@qq.com>
Project-URL: Homepage, https://github.com/ww-rm/ncmdump-py
Project-URL: Issues, https://github.com/ww-rm/ncmdump-py/issues
Requires-Python: >=3.7
License-File: LICENSE
Requires-Dist: mutagen
Requires-Dist: Pillow
Requires-Dist: pycryptodome
Requires-Dist: rich
Dynamic: license-file
